SCoinAPI/__init__.py
SCoinAPI/bank.py
SCoinAPI/centralbank.py
SCoinAPI/retailer.py
SCoinAPI-1.2.3.dist-info/LICENSE.txt
SCoinAPI-1.2.3.dist-info/METADATA
SCoinAPI-1.2.3.dist-info/WHEEL
SCoinAPI-1.2.3.dist-info/top_level.txt
SCoinAPI-1.2.3.dist-info/RECORD
