Metadata-Version: 2.1
Name: SCoinAPI
Version: 1.2.3
Summary: The light package for the SCU blockchain in the IOTA system.
Home-page: https://github.com/sefx5ever/SCoinAPI.git
Author: Wyne Tan
Author-email: sefx5ever@gmail.com
License: UNKNOWN
Platform: UNKNOWN
Classifier: Programming Language :: Python
Classifier: Programming Language :: Python :: 3
Classifier: Programming Language :: Python :: 3.4
Classifier: Programming Language :: Python :: 3.5
Classifier: Programming Language :: Python :: 3.6
Classifier: Programming Language :: Python :: 3.7
Classifier: Programming Language :: Python :: 3.8
Classifier: Programming Language :: Python :: 3.9
Classifier: License :: OSI Approved :: MIT License
Classifier: Operating System :: OS Independent
Requires-Dist: requests (>=2.23.0)
